Selenium_Scraper/Selenium_Scraper.py
Selenium_Scraper/__about__.py
Selenium_Scraper/__init__.py
selenium_scraper-0.0.11.dist-info/METADATA
selenium_scraper-0.0.11.dist-info/WHEEL
selenium_scraper-0.0.11.dist-info/licenses/LICENSE
selenium_scraper-0.0.11.dist-info/RECORD
