Metadata-Version: 2.1
Name: Selenium_Scraper
Version: 0.0.11
Summary: Selenium Scraper
Author-email: Sabari Rajan <iamsabarirajan@gmail.com>
License: MIT License
License-File: LICENSE
Keywords: scraper,selenium,web,webscraper
Requires-Dist: selenium
Requires-Dist: webdriver-manager
